feature_lens-0.2.0.dist-info/METADATA
feature_lens-0.2.0.dist-info/WHEEL
feature_lens/__init__.py
feature_lens/ablate.py
feature_lens/attribute.py
feature_lens/cache.py
feature_lens/core/types.py
feature_lens/data/handler.py
feature_lens/data/metric.py
feature_lens/data/toy_datasets/__init__.py
feature_lens/data/toy_datasets/ioi.py
feature_lens/nn/transcoder/__init__.py
feature_lens/nn/transcoder/load_pretrained.py
feature_lens/nn/transcoder/sae_training/__init__.py
feature_lens/nn/transcoder/sae_training/config.py
feature_lens/nn/transcoder/sae_training/sparse_autoencoder.py
feature_lens/nn/transcoder/transcoder.py
feature_lens/utils/data_utils.py
feature_lens/utils/device.py
feature_lens/utils/load_pretrained.py
feature_lens/utils/memory.py
feature_lens/utils/neuronpedia.py
feature_lens/utils/viz.py
feature_lens-0.2.0.dist-info/RECORD
