Metadata-Version: 2.1
Name: feature-lens
Version: 0.2.0
Summary: In-depth visualizations for SAE features
Author-Email: Daniel Tan <dtch1997@users.noreply.github.com>
License: MIT
Requires-Python: ==3.11.*
Requires-Dist: pre-commit>=3.7.1
Requires-Dist: transformer-lens>=2.2.2
Requires-Dist: sae-lens>=3.12.1
Requires-Dist: eindex-callum>=0.1.2
Requires-Dist: circuitsvis>=1.43.2
Requires-Dist: torch>=2.1.2
Requires-Dist: ipykernel>=6.29.5
Requires-Dist: pip>=24.1.2
Requires-Dist: nbconvert>=7.16.4
Requires-Dist: notebook>=7.2.1
Requires-Dist: seaborn>=0.13.2
Requires-Dist: streamlit>=1.36.0
Requires-Dist: networkx>=3.3
Requires-Dist: ruff>=0.4.3; extra == "test"
Requires-Dist: pytest>=8.2.0; extra == "test"
Requires-Dist: pyright>=1.1.361; extra == "test"
Provides-Extra: test
